{
"type": "FeatureCollection",
"name": "baikal_danger_harbormamai",
"crs": { "type": "name", "properties": { "name": "urn:ogc:def:crs:OGC:1.3:CRS84" } },
"features": [
{ "type": "Feature", "properties": { "id": 0, "maptext": "Существующие участки особых экономических зон (Бухта Безымянная)", "maptext_en": "Bezymyannaya Bay" }, "geometry": { "type": "Point", "coordinates": [ 108.329228633001762, 53.024843119637318 ] } },
{ "type": "Feature", "properties": { "id": 2, "maptext": "Существующие участки особых экономических зон (Горячинск)", "maptext_en": "Goryachinsk" }, "geometry": { "type": "Point", "coordinates": [ 108.297461787795598, 52.989739662763142 ] } },
{ "type": "Feature", "properties": { "id": 3, "maptext": "Существующие участки особых экономических зон (Турка)", "maptext_en": "Turka" }, "geometry": { "type": "Point", "coordinates": [ 108.224906041574258, 52.938474903219728 ] } },
{ "type": "Feature", "properties": { "id": 4, "maptext": "Существующие участки особых экономических зон (Пески)", "maptext_en": "Peski" }, "geometry": { "type": "Point", "coordinates": [ 108.158282114490916, 52.904792114226701 ] } },
{ "type": "Feature", "properties": { "id": 5, "maptext": "Существующие участки особых экономических зон (гора Бычья)", "maptext_en": "Bychya mountain" }, "geometry": { "type": "Point", "coordinates": [ 108.172314608365795, 52.615815978575121 ] } },
{ "type": "Feature", "properties": { "id": 6, "maptext": "Планируемое расширение ОЭЗ «Байкальская Гавань» (гора Мамай)", "maptext_en": "Proposed expansion SEZ «Baikal harbor» on the mountain Mamay" }, "geometry": { "type": "Point", "coordinates": [ 104.785297821640611, 51.450327118250762 ] } }
]
}
